Workbook

Sheet asunciones
A1: asunciones — drivers del modelo financiero
A2: actualiza acá las asunciones; el resto de hojas leen de aquí
A4: concepto | B4: valor | C4: unidad | D4: notas
A5: tipo de cambio
A6: MXN por USD | B6: 22 | C6: MXN/USD | D6: ajustar mensual con dato real
A8: cash & runway
A9: cash inicial (MXN) | B9: 22500 | C9: MXN | D9: saldo en cuenta al cierre del mes anterior
A10: burn técnico mensual (MXN) | B10: 9000 | C10: MXN | D10: infra + saas (anthropic, supabase, vercel, etc.)
A11: image generation budget (USD) | B11: 150 | C11: USD | D11: Recraft + Flux/Replicate + buffer
A12: marketing budget (USD) | B12: 0 | C12: USD | D12: 100% orgánico fase 1; subir si Pablo aprueba
A13: inflow externo mensual (MXN) | B13: 55000 | C13: MXN | D13: capital aporte, no revenue de itera
A14: trigger plan B (meses sin inflow) | B14: 1 | C14: meses | D14: si pasa este # de meses sin inflow, se activa downside
A16: pricing matrix (USD)
A17: free tier | B17: 0 | C17: USD/mes | D17: trial / champion seed
A18: prosumer mensual | B18: 29 | C18: USD/mes | D18: individuos serios; sin custom curriculum, sin operación
A19: prosumer anual | B19: 290 | C19: USD/año | D19: $24/mes equivalente
A20: team B2B (5-19 seats) | B20: 39 | C20: USD/seat/mes | D20: anual prepagado = $420/seat/año
A21: business B2B (20-99 seats) | B21: 29 | C21: USD/seat/mes | D21: anual prepagado = $348/seat/año + BYOK
A22: enterprise (100+) | B22: 19 | C22: USD/seat/mes | D22: custom desde este piso
A24: unit economics
A25: gross margin target | B25: 0.85 | C25: % | D25: objetivo blended; BYOK ayuda a llegar
A26: COGS por usuario activo (USD) | B26: 4 | C26: USD/mes | D26: anthropic + openai + cohere prorrateado
A27: conversión free → paid (B2C) | B27: 0.03 | C27: % | D27: asumido; validar con primer mes de tráfico
A28: churn mensual prosumer | B28: 0.07 | C28: % | D28: B2C edtech típico LATAM
A29: churn anual B2B team | B29: 0.15 | C29: % | D29: B2B SaaS LATAM mid-market
A31: régimen fiscal RIF (México)
A32: tope RIF anual (MXN) | B32: 3500000 | C32: MXN | D32: techo legal; arriba se migra a persona moral
A33: tope RIF anual (USD) | B33: =asunciones!$B$32/asunciones!$B$6 | C33: USD | D33: calculado al tipo de cambio actual
A34: trigger migración (% del tope) | B34: 0.7 | C34: % | D34: arrancar plan migración al llegar a este nivel

Sheet costos_mensuales
A1: costos mensuales por proveedor (USD)
A2: celdas amarillas = pegar factura real cuando llegue. estimaciones de arranque en azul.
A4: proveedor | B4: categoría | C4: tipo | D4: abr-26 | E4: may-26 | F4: jun-26 | G4: jul-26 | H4: ago-26 | I4: sep-26 | J4: oct-26 | K4: nov-26 | L4: dic-26 | M4: ene-27 | N4: feb-27 | O4: mar-27
A5: Anthropic API | B5: AI provider | C5: variable | D5: 60
A6: OpenAI (embeddings + completion) | B6: AI provider | C6: variable | D6: 15
A7: Cohere (rerank) | B7: AI provider | C7: variable | D7: 10
A8: Supabase | B8: infra | C8: fijo | D8: 25
A9: Vercel | B9: infra | C9: fijo | D9: 20
A10: AgentMail | B10: infra | C10: fijo | D10: 10
A11: Recraft v4 | B11: content tools | C11: variable | D11: 30
A12: Flux/Replicate | B12: content tools | C12: variable | D12: 50
A13: Dominios (.la, .com) | B13: infra | C13: fijo | D13: 2
A14: Claude.ai / Codex / Perplexity | B14: tooling personal | C14: fijo | D14: 80
A15: otros SaaS | B15: varios | C15: fijo | D15: 0
A16: TOTAL | D16: =SUM(D5:D15) | E16: =SUM(E5:E15) | F16: =SUM(F5:F15) | G16: =SUM(G5:G15) | H16: =SUM(H5:H15) | I16: =SUM(I5:I15) | J16: =SUM(J5:J15) | K16: =SUM(K5:K15) | ... O16: =SUM(O5:O15)
A17: TOTAL (MXN) | D17: =D16*asunciones!$B$6 | E17: =E16*asunciones!$B$6 | F17: =F16*asunciones!$B$6 | G17: =G16*asunciones!$B$6 | H17: =H16*asunciones!$B$6 | I17: =I16*asunciones!$B$6 | J17: =J16*asunciones!$B$6 | K17: =K16*asunciones!$B$6 | ... O17: =O16*asunciones!$B$6

Sheet cash_flow
A1: cash flow mensual (MXN)
A2: todo en MXN. inflow externo es 'capital aporte' (no revenue de itera). los costos vienen de la hoja costos_mensuales × tipo de cambio.
A4: concepto | B4: abr-26 | C4: may-26 | D4: jun-26 | E4: jul-26 | F4: ago-26 | G4: sep-26 | H4: oct-26 | I4: nov-26 | J4: dic-26 | K4: ene-27 | L4: feb-27 | M4: mar-27
A5: ENTRADAS
A6: inflow externo (Pablo-as-VC) | B6: =asunciones!$B$13 | C6: =asunciones!$B$13 | D6: =asunciones!$B$13 | E6: =asunciones!$B$13 | F6: =asunciones!$B$13 | G6: =asunciones!$B$13 | H6: =asunciones!$B$13 | I6: =asunciones!$B$13 | ... M6: =asunciones!$B$13
A7: revenue itera (placeholder) | B7: 0 | C7: 0 | D7: 0 | E7: 0 | F7: 0 | G7: 0 | H7: 0 | I7: 0 | J7: 0 | K7: 0 | L7: 0 | M7: 0
A8: total entradas | B8: =SUM(B6:B7) | C8: =SUM(C6:C7) | D8: =SUM(D6:D7) | E8: =SUM(E6:E7) | F8: =SUM(F6:F7) | G8: =SUM(G6:G7) | H8: =SUM(H6:H7) | I8: =SUM(I6:I7) | ... M8: =SUM(M6:M7)
A10: SALIDAS
A11: burn técnico (infra + AI) | B11: =costos_mensuales!D16*asunciones!$B$6 | C11: =costos_mensuales!E16*asunciones!$B$6 | D11: =costos_mensuales!F16*asunciones!$B$6 | E11: =costos_mensuales!G16*asunciones!$B$6 | F11: =costos_mensuales!H16*asunciones!$B$6 | G11: =costos_mensuales!I16*asunciones!$B$6 | H11: =costos_mensuales!J16*asunciones!$B$6 | I11: =costos_mensuales!K16*asunciones!$B$6 | ... M11: =costos_mensuales!O16*asunciones!$B$6
A12: marketing | B12: =asunciones!$B$12*asunciones!$B$6 | C12: =asunciones!$B$12*asunciones!$B$6 | D12: =asunciones!$B$12*asunciones!$B$6 | E12: =asunciones!$B$12*asunciones!$B$6 | F12: =asunciones!$B$12*asunciones!$B$6 | G12: =asunciones!$B$12*asunciones!$B$6 | H12: =asunciones!$B$12*asunciones!$B$6 | I12: =asunciones!$B$12*asunciones!$B$6 | ... M12: =asunciones!$B$12*asunciones!$B$6
A13: total salidas | B13: =SUM(B11:B12) | C13: =SUM(C11:C12) | D13: =SUM(D11:D12) | E13: =SUM(E11:E12) | F13: =SUM(F11:F12) | G13: =SUM(G11:G12) | H13: =SUM(H11:H12) | I13: =SUM(I11:I12) | ... M13: =SUM(M11:M12)
A15: NETO MENSUAL | B15: =B8-B13 | C15: =C8-C13 | D15: =D8-D13 | E15: =E8-E13 | F15: =F8-F13 | G15: =G8-G13 | H15: =H8-H13 | I15: =I8-I13 | ... M15: =M8-M13
A16: CASH ACUMULADO | B16: =asunciones!$B$9+B15 | C16: =B16+C15 | D16: =C16+D15 | E16: =D16+E15 | F16: =E16+F15 | G16: =F16+G15 | H16: =G16+H15 | I16: =H16+I15 | J16: =I16+J15 | ... M16: =L16+M15
A18: runway si inflow = 0 (meses) | B18: =IF(B13=0,0,B16/B13) | C18: =IF(C13=0,0,C16/C13) | D18: =IF(D13=0,0,D16/D13) | E18: =IF(E13=0,0,E16/E13) | F18: =IF(F13=0,0,F16/F13) | G18: =IF(G13=0,0,G16/G13) | H18: =IF(H13=0,0,H16/H13) | I18: =IF(I13=0,0,I16/I13) | ... M18: =IF(M13=0,0,M16/M13)

Sheet pipeline_b2b
A1: pipeline B2B
A2: fases: lead → demo → propuesta → piloto → contrato. ACV = annual contract value (USD).
A4: empresa | B4: contacto | C4: fase | D4: seats est. | E4: ACV potencial USD | F4: siguiente paso | G4: fecha próxima | H4: notas
A21: TOTAL ACV pipeline (USD) | E21: =SUM(E5:E19)
A22: ACV ponderado (50% probabilidad) | E22: =E21*0.5

Sheet pricing_matrix
A1: pricing matrix v1 (propuesta — pendiente OK de Pablo)
A2: comps: CEO encontró que LATAM mid-market upskilling paga $300-800/empleado/año (mediana ~$500). itera estaba subdimensionado a $200/año. headroom defendible: $400-500/año.
A4: tier | B4: $/mes | C4: $/año | D4: seats | E4: gating / qué incluye | F4: margen target
A5: free / trial | B5: 0 | C5: 0 | D5: 1 user | E5: 1 sección, sin AI tutor, sin operación, sin progreso persistente | F5: 0
A6: prosumer mensual | B6: 29 | C6: 348 | D6: 1 user | E6: self-serve; sin custom curriculum; sin BYOK; sin SSO | F6: 0.75
A7: prosumer anual | B7: 24 | C7: 290 | D7: 1 user | E7: self-serve; descuento por anual prepagado | F7: 0.78
A8: team B2B | B8: 39 | C8: 420 | D8: 5-19 | E8: custom curriculum lite; dashboard; billing centralizado | F8: 0.8
A9: business B2B | B9: 29 | C9: 348 | D9: 20-99 | E9: custom curriculum; BYOK operación; SSO opcional | F9: 0.75
A10: enterprise | B10: 19 | C10: 228 | D10: 100+ | E10: full custom; CSM dedicado; SLA; integraciones | F10: 0.7

Sheet modelo_forecast
A1: modelo forecast 12 meses — 3 escenarios
A2: valores en USD para comparabilidad. base = inflow estable + 0 revenue. downside = inflow se cae mes 4. upside = primer cliente B2B team mes 3.
A4: concepto | B4: abr-26 | C4: may-26 | D4: jun-26 | E4: jul-26 | F4: ago-26 | G4: sep-26 | H4: oct-26 | I4: nov-26 | J4: dic-26 | K4: ene-27 | L4: feb-27 | M4: mar-27
A5: ESCENARIO BASE — inflow estable, sin revenue B2B
A6: inflow externo (USD) | B6: =asunciones!$B$13/asunciones!$B$6*1 | C6: =asunciones!$B$13/asunciones!$B$6*1 | D6: =asunciones!$B$13/asunciones!$B$6*1 | E6: =asunciones!$B$13/asunciones!$B$6*1 | F6: =asunciones!$B$13/asunciones!$B$6*1 | G6: =asunciones!$B$13/asunciones!$B$6*1 | H6: =asunciones!$B$13/asunciones!$B$6*1 | I6: =asunciones!$B$13/asunciones!$B$6*1 | ... M6: =asunciones!$B$13/asunciones!$B$6*1
A7: seats B2B activos | B7: =0 | C7: =0 | D7: =0 | E7: =0 | F7: =0 | G7: =0 | H7: =0 | I7: =0 | ... M7: =0
A8: revenue B2B team (USD) | B8: =B7*asunciones!$B$20 | C8: =C7*asunciones!$B$20 | D8: =D7*asunciones!$B$20 | E8: =E7*asunciones!$B$20 | F8: =F7*asunciones!$B$20 | G8: =G7*asunciones!$B$20 | H8: =H7*asunciones!$B$20 | I8: =I7*asunciones!$B$20 | ... M8: =M7*asunciones!$B$20
A9: burn técnico (USD) | B9: =costos_mensuales!D16 | C9: =costos_mensuales!E16 | D9: =costos_mensuales!F16 | E9: =costos_mensuales!G16 | F9: =costos_mensuales!H16 | G9: =costos_mensuales!I16 | H9: =costos_mensuales!J16 | I9: =costos_mensuales!K16 | ... M9: =costos_mensuales!O16
A10: COGS variable (B2B users × COGS/user) | B10: =B7*asunciones!$B$26 | C10: =C7*asunciones!$B$26 | D10: =D7*asunciones!$B$26 | E10: =E7*asunciones!$B$26 | F10: =F7*asunciones!$B$26 | G10: =G7*asunciones!$B$26 | H10: =H7*asunciones!$B$26 | I10: =I7*asunciones!$B$26 | ... M10: =M7*asunciones!$B$26
A11: marketing (USD) | B11: =asunciones!$B$12+asunciones!$B$11 | C11: =asunciones!$B$12+asunciones!$B$11 | D11: =asunciones!$B$12+asunciones!$B$11 | E11: =asunciones!$B$12+asunciones!$B$11 | F11: =asunciones!$B$12+asunciones!$B$11 | G11: =asunciones!$B$12+asunciones!$B$11 | H11: =asunciones!$B$12+asunciones!$B$11 | I11: =asunciones!$B$12+asunciones!$B$11 | ... M11: =asunciones!$B$12+asunciones!$B$11
A12: NETO (USD) | B12: =B6+B8-B9-B10-B11 | C12: =C6+C8-C9-C10-C11 | D12: =D6+D8-D9-D10-D11 | E12: =E6+E8-E9-E10-E11 | F12: =F6+F8-F9-F10-F11 | G12: =G6+G8-G9-G10-G11 | H12: =H6+H8-H9-H10-H11 | I12: =I6+I8-I9-I10-I11 | ... M12: =M6+M8-M9-M10-M11
A13: CASH ACUMULADO (USD) | B13: =asunciones!$B$9/asunciones!$B$6+B12 | C13: =B13+C12 | D13: =C13+D12 | E13: =D13+E12 | F13: =E13+F12 | G13: =F13+G12 | H13: =G13+H12 | I13: =H13+I12 | J13: =I13+J12 | ... M13: =L13+M12
A15: ESCENARIO DOWNSIDE — inflow cae mes 4
A16: inflow externo (USD) | B16: =asunciones!$B$13/asunciones!$B$6*1 | C16: =asunciones!$B$13/asunciones!$B$6*1 | D16: =asunciones!$B$13/asunciones!$B$6*1 | E16: =asunciones!$B$13/asunciones!$B$6*0 | F16: =asunciones!$B$13/asunciones!$B$6*0 | G16: =asunciones!$B$13/asunciones!$B$6*0 | H16: =asunciones!$B$13/asunciones!$B$6*0 | I16: =asunciones!$B$13/asunciones!$B$6*0 | J16: =asunciones!$B$13/asunciones!$B$6*0 | K16: =asunciones!$B$13/asunciones!$B$6*0 | L16: =asunciones!$B$13/asunciones!$B$6*0 | M16: =asunciones!$B$13/asunciones!$B$6*0
A17: seats B2B activos | B17: =0 | C17: =0 | D17: =0 | E17: =0 | F17: =0 | G17: =0 | H17: =0 | I17: =0 | ... M17: =0
A18: revenue B2B team (USD) | B18: =B17*asunciones!$B$20 | C18: =C17*asunciones!$B$20 | D18: =D17*asunciones!$B$20 | E18: =E17*asunciones!$B$20 | F18: =F17*asunciones!$B$20 | G18: =G17*asunciones!$B$20 | H18: =H17*asunciones!$B$20 | I18: =I17*asunciones!$B$20 | ... M18: =M17*asunciones!$B$20
A19: burn técnico (USD) | B19: =costos_mensuales!D16 | C19: =costos_mensuales!E16 | D19: =costos_mensuales!F16 | E19: =costos_mensuales!G16 | F19: =costos_mensuales!H16 | G19: =costos_mensuales!I16 | H19: =costos_mensuales!J16 | I19: =costos_mensuales!K16 | ... M19: =costos_mensuales!O16
A20: COGS variable (B2B users × COGS/user) | B20: =B17*asunciones!$B$26 | C20: =C17*asunciones!$B$26 | D20: =D17*asunciones!$B$26 | E20: =E17*asunciones!$B$26 | F20: =F17*asunciones!$B$26 | G20: =G17*asunciones!$B$26 | H20: =H17*asunciones!$B$26 | I20: =I17*asunciones!$B$26 | ... M20: =M17*asunciones!$B$26
A21: marketing (USD) | B21: =asunciones!$B$12+asunciones!$B$11 | C21: =asunciones!$B$12+asunciones!$B$11 | D21: =asunciones!$B$12+asunciones!$B$11 | E21: =asunciones!$B$12+asunciones!$B$11 | F21: =asunciones!$B$12+asunciones!$B$11 | G21: =asunciones!$B$12+asunciones!$B$11 | H21: =asunciones!$B$12+asunciones!$B$11 | I21: =asunciones!$B$12+asunciones!$B$11 | ... M21: =asunciones!$B$12+asunciones!$B$11
A22: NETO (USD) | B22: =B16+B18-B19-B20-B21 | C22: =C16+C18-C19-C20-C21 | D22: =D16+D18-D19-D20-D21 | E22: =E16+E18-E19-E20-E21 | F22: =F16+F18-F19-F20-F21 | G22: =G16+G18-G19-G20-G21 | H22: =H16+H18-H19-H20-H21 | I22: =I16+I18-I19-I20-I21 | ... M22: =M16+M18-M19-M20-M21
A23: CASH ACUMULADO (USD) | B23: =asunciones!$B$9/asunciones!$B$6+B22 | C23: =B23+C22 | D23: =C23+D22 | E23: =D23+E22 | F23: =E23+F22 | G23: =F23+G22 | H23: =G23+H22 | I23: =H23+I22 | J23: =I23+J22 | ... M23: =L23+M22
A25: ESCENARIO UPSIDE — primer cliente B2B 10 seats mes 3
A26: inflow externo (USD) | B26: =asunciones!$B$13/asunciones!$B$6*1 | C26: =asunciones!$B$13/asunciones!$B$6*1 | D26: =asunciones!$B$13/asunciones!$B$6*1 | E26: =asunciones!$B$13/asunciones!$B$6*1 | F26: =asunciones!$B$13/asunciones!$B$6*1 | G26: =asunciones!$B$13/asunciones!$B$6*1 | H26: =asunciones!$B$13/asunciones!$B$6*1 | I26: =asunciones!$B$13/asunciones!$B$6*1 | ... M26: =asunciones!$B$13/asunciones!$B$6*1
A27: seats B2B activos | B27: =0 | C27: =0 | D27: 10 | E27: =D27+10 | F27: =E27+10 | G27: =F27+10 | H27: =G27+10 | I27: =H27+10 | J27: =I27+10 | K27: =J27+10 | L27: =K27+10 | M27: =L27+10
A28: revenue B2B team (USD) | B28: =B27*asunciones!$B$20 | C28: =C27*asunciones!$B$20 | D28: =D27*asunciones!$B$20 | E28: =E27*asunciones!$B$20 | F28: =F27*asunciones!$B$20 | G28: =G27*asunciones!$B$20 | H28: =H27*asunciones!$B$20 | I28: =I27*asunciones!$B$20 | ... M28: =M27*asunciones!$B$20
A29: burn técnico (USD) | B29: =costos_mensuales!D16 | C29: =costos_mensuales!E16 | D29: =costos_mensuales!F16 | E29: =costos_mensuales!G16 | F29: =costos_mensuales!H16 | G29: =costos_mensuales!I16 | H29: =costos_mensuales!J16 | I29: =costos_mensuales!K16 | ... M29: =costos_mensuales!O16
A30: COGS variable (B2B users × COGS/user) | B30: =B27*asunciones!$B$26 | C30: =C27*asunciones!$B$26 | D30: =D27*asunciones!$B$26 | E30: =E27*asunciones!$B$26 | F30: =F27*asunciones!$B$26 | G30: =G27*asunciones!$B$26 | H30: =H27*asunciones!$B$26 | I30: =I27*asunciones!$B$26 | ... M30: =M27*asunciones!$B$26
A31: marketing (USD) | B31: =asunciones!$B$12+asunciones!$B$11 | C31: =asunciones!$B$12+asunciones!$B$11 | D31: =asunciones!$B$12+asunciones!$B$11 | E31: =asunciones!$B$12+asunciones!$B$11 | F31: =asunciones!$B$12+asunciones!$B$11 | G31: =asunciones!$B$12+asunciones!$B$11 | H31: =asunciones!$B$12+asunciones!$B$11 | I31: =asunciones!$B$12+asunciones!$B$11 | ... M31: =asunciones!$B$12+asunciones!$B$11
A32: NETO (USD) | B32: =B26+B28-B29-B30-B31 | C32: =C26+C28-C29-C30-C31 | D32: =D26+D28-D29-D30-D31 | E32: =E26+E28-E29-E30-E31 | F32: =F26+F28-F29-F30-F31 | G32: =G26+G28-G29-G30-G31 | H32: =H26+H28-H29-H30-H31 | I32: =I26+I28-I29-I30-I31 | ... M32: =M26+M28-M29-M30-M31
A33: CASH ACUMULADO (USD) | B33: =asunciones!$B$9/asunciones!$B$6+B32 | C33: =B33+C32 | D33: =C33+D32 | E33: =D33+E32 | F33: =E33+F32 | G33: =F33+G32 | H33: =G33+H32 | I33: =H33+I32 | J33: =I33+J32 | ... M33: =L33+M32
